LICENSE
tgintegration/__init__.py
tgintegration/botcontroller.py
tgintegration/collector.py
tgintegration/containers/__init__.py
tgintegration/containers/exceptions.py
tgintegration/containers/inline_keyboard.py
tgintegration/containers/inlineresults.py
tgintegration/containers/reply_keyboard.py
tgintegration/containers/responses.py
tgintegration/expectation.py
tgintegration/handler_utils.py
tgintegration/timeout_settings.py
tgintegration/update_recorder.py
tgintegration/utils/__init__.py
tgintegration/utils/frame_utils.py
tgintegration/utils/iter_utils.py
tgintegration/utils/sentinel.py
tgintegration-1.2.0.dist-info/LICENSE
tgintegration-1.2.0.dist-info/WHEEL
tgintegration-1.2.0.dist-info/METADATA
tgintegration-1.2.0.dist-info/RECORD
