Metadata-Version: 2.1
Name: tgintegration
Version: 1.2.0
Summary: Integration test and automation library for Telegram Messenger Bots based on Pyrogram.
Home-page: https://github.com/JosXa/tgintegration
License: MIT
Keywords: telegram-bots,testing,integration-tests,library,python
Author: JosXa
Author-email: joscha.goetzer@gmail.com
Requires-Python: >=3.7,<4.0.0
Classifier: Intended Audience :: Developers
Classifier: License :: OSI Approved :: MIT License
Classifier: Programming Language :: Python :: 3
Classifier: Programming Language :: Python :: 3.10
Classifier: Programming Language :: Python :: 3.7
Classifier: Programming Language :: Python :: 3.8
Classifier: Programming Language :: Python :: 3.9
Classifier: Programming Language :: Python :: Implementation :: CPython
Classifier: Topic :: Software Development :: Libraries :: Python Modules
Classifier: Typing :: Typed
Requires-Dist: pyrogram (>=1.0.0,<2.0.0)
Requires-Dist: typing-extensions (>=3.7.4,<4.0.0)
Project-URL: Bug Tracker, https://github.com/JosXa/tgintegration/issues
Project-URL: Contact Author, https:/t.me/JosXa
Project-URL: Repository, https://github.com/JosXa/tgintegration
Project-URL: Support Chat, https://t.me/TgIntegration
